l3mon/__init__.py
l3mon/main.py
l3mon-0.0.1.dist-info/METADATA
l3mon-0.0.1.dist-info/WHEEL
l3mon-0.0.1.dist-info/entry_points.txt
l3mon-0.0.1.dist-info/top_level.txt
l3mon-0.0.1.dist-info/RECORD
