Metadata-Version: 2.4
Name: l3mon
Version: 0.0.1
Summary: L3mon Android Security Test Script Auto-Installer
Author: EFXTV
Requires-Python: >=3.7
